<!-- racacax\XmlTv\Component\Provider\Afrique -->
<programme start="20230506080750 +0200" stop="20230506083050 +0200" channel="CanalPlusActionCentre.af">
<title lang="fr">Malabar</title>
<desc lang="fr">Aucune description</desc>
<category lang="fr">Inconnu</category>
<icon src="https://service.canal-overseas.com/image-api/v1/image/040ece9c9098cc8e097e1940b71e5c8f" />
</programme>
<programme start="20230506083214 +0200" stop="20230506092914 +0200" channel="CanalPlusActionCentre.af">
<title lang="fr">Power Book II : Ghost - S2 - Ep5</title>
<desc lang="fr">Aucune description</desc>
<category lang="fr">Inconnu</category>
<icon src="https://service.canal-overseas.com/image-api/v1/image/5535b59e9c9da649dde8b3c5665f5c0a" />
</programme>
<programme start="20230506092937 +0200" stop="20230506102537 +0200" channel="CanalPlusActionCentre.af">
<title lang="fr">Power Book II : Ghost - S2 - Ep6</title>
<desc lang="fr">Aucune description</desc>
<category lang="fr">Inconnu</category>
<icon src="https://service.canal-overseas.com/image-api/v1/image/1724ad4ddbd12737c1e72d84b0c751ac" />
</programme>
<programme start="20230506102633 +0200" stop="20230506110633 +0200" channel="CanalPlusActionCentre.af">
<title lang="fr">Six - S1 - Ep5</title>
<desc lang="fr">Aucune description</desc>
<category lang="fr">Inconnu</category>
<icon src="https://service.canal-overseas.com/image-api/v1/image/0c596cca8834fce66410535abf53fa0b" />
</programme>
<programme start="20230506110729 +0200" stop="20230506114829 +0200" channel="CanalPlusActionCentre.af">
<title lang="fr">Six - S1 - Ep6</title>
<desc lang="fr">Aucune description</desc>
<category lang="fr">Inconnu</category>
<icon src="https://service.canal-overseas.com/image-api/v1/image/7f7ba296b198722d7d3cb1bb367f20ab" />
</programme>
<programme start="20230506114918 +0200" stop="20230506133818 +0200" channel="CanalPlusActionCentre.af">
<title lang="fr">Adiós</title>
<desc lang="fr">Aucune description</desc>
<category lang="fr">Inconnu</category>
<icon src="https://service.canal-overseas.com/image-api/v1/image/9de866e434059520c9afb62390257db5" />
</programme>
<programme start="20230506134157 +0200" stop="20230506141857 +0200" channel="CanalPlusActionCentre.af">
<title lang="fr">Halo - S1 - Ep5</title>
<desc lang="fr">Aucune description</desc>
<category lang="fr">Inconnu</category>
<icon src="https://service.canal-overseas.com/image-api/v1/image/f99312a778488a5c5c05292dfa7d6f94" />
</programme>
<programme start="20230506141949 +0200" stop="20230506150549 +0200" channel="CanalPlusActionCentre.af">
<title lang="fr">Halo - S1 - Ep6</title>
<desc lang="fr">Aucune description</desc>
<category lang="fr">Inconnu</category>
<icon src="https://service.canal-overseas.com/image-api/v1/image/24fdbff3661e0671bccdbdbfc7551677" />
</programme>
<programme start="20230506151300 +0200" stop="20230506155200 +0200" channel="CanalPlusActionCentre.af">
<title lang="fr">Most Wanted Criminals - S3 - Ep8</title>
<desc lang="fr">Aucune description</desc>
<category lang="fr">Inconnu</category>
<icon src="https://service.canal-overseas.com/image-api/v1/image/e355f2d86a9a9ec5645c078a53c01bb1" />
</programme>
<programme start="20230506155358 +0200" stop="20230506165058 +0200" channel="CanalPlusActionCentre.af">
<title lang="fr">Power Book II : Ghost - S2 - Ep7</title>
<desc lang="fr">Aucune description</desc>
<category lang="fr">Inconnu</category>
<icon src="https://service.canal-overseas.com/image-api/v1/image/5f56a1c16fc304ee9e491229216bcb99" />
</programme>
<programme start="20230506165137 +0200" stop="20230506174537 +0200" channel="CanalPlusActionCentre.af">
<title lang="fr">Power Book II : Ghost - S2 - Ep8</title>
<desc lang="fr">Aucune description</desc>
<category lang="fr">Inconnu</category>
<icon src="https://service.canal-overseas.com/image-api/v1/image/411c920869693aa503ce926431b7870f" />
</programme>
<programme start="20230506174629 +0200" stop="20230506180029 +0200" channel="CanalPlusActionCentre.af">
<title lang="fr">973</title>
<desc lang="fr">Aucune description</desc>
<category lang="fr">Inconnu</category>
<icon src="https://service.canal-overseas.com/image-api/v1/image/a941675417ba34b12b3bd2147ca736a0" />
</programme>
<programme start="20230506180203 +0200" stop="20230506194803 +0200" channel="CanalPlusActionCentre.af">
<title lang="fr">Le coup de maître</title>
<desc lang="fr">Aucune description</desc>
<category lang="fr">Inconnu</category>
<icon src="https://service.canal-overseas.com/image-api/v1/image/e08d474cd95dae420f5a9548b248e806" />
</programme>
<programme start="20230506195300 +0200" stop="20230506204400 +0200" channel="CanalPlusActionCentre.af">
<title lang="fr">Top Gear</title>
<desc lang="fr">Aucune description</desc>
<category lang="fr">Inconnu</category>
<icon src="https://service.canal-overseas.com/image-api/v1/image/751777c5f6c62d26963500861a10b158" />
</programme>
<programme start="20230506204600 +0200" stop="20230506212600 +0200" channel="CanalPlusActionCentre.af">
<title lang="fr">Most Wanted Criminals - S3 - Ep10</title>
<desc lang="fr">Aucune description</desc>
<category lang="fr">Inconnu</category>
<icon src="https://service.canal-overseas.com/image-api/v1/image/6296601a2f646840bdf4bcbc6ba6a04f" />
</programme>
<programme start="20230506213000 +0200" stop="20230506221000 +0200" channel="CanalPlusActionCentre.af">
<title lang="fr">Six - S1 - Ep7</title>
<desc lang="fr">Aucune description</desc>
<category lang="fr">Inconnu</category>
<icon src="https://service.canal-overseas.com/image-api/v1/image/3d0c2a4e75242406bc6035224437a1e7" />
</programme>
<programme start="20230506221048 +0200" stop="20230506225248 +0200" channel="CanalPlusActionCentre.af">
<title lang="fr">Six - S1 - Ep8</title>
<desc lang="fr">Aucune description</desc>
<category lang="fr">Inconnu</category>
<icon src="https://service.canal-overseas.com/image-api/v1/image/c96f50f8e557b3c328d455eb98bc33b1" />
</programme>
<programme start="20230506225529 +0200" stop="20230507010829 +0200" channel="CanalPlusActionCentre.af">
<title lang="fr">Asura : The City of Madness</title>
<desc lang="fr">Aucune description</desc>
<category lang="fr">Inconnu</category>
<icon src="https://service.canal-overseas.com/image-api/v1/image/e76fe2de1288bd6d01e9fdbdd544f43f" />
</programme>
<programme start="20230507011111 +0200" stop="20230507015111 +0200" channel="CanalPlusActionCentre.af">
<title lang="fr">Fear The Walking Dead - S2 - Ep14</title>
<desc lang="fr">Aucune description</desc>
<category lang="fr">Inconnu</category>
<icon src="https://service.canal-overseas.com/image-api/v1/image/af2abd688d805a6eb7946b88b9076cbf" />
</programme>
<programme start="20230507015135 +0200" stop="20230507023435 +0200" channel="CanalPlusActionCentre.af">
<title lang="fr">Fear The Walking Dead - S2 - Ep15</title>
<desc lang="fr">Aucune description</desc>
<category lang="fr">Inconnu</category>
<icon src="https://service.canal-overseas.com/image-api/v1/image/a69370c0b302ec538d630bfa2a46c80a" />
</programme>
<programme start="20230507023605 +0200" stop="20230507032105 +0200" channel="CanalPlusActionCentre.af">
<title lang="fr">Fear The Walking Dead - S3 - Ep1</title>
<desc lang="fr">Aucune description</desc>
<category lang="fr">Inconnu</category>
<icon src="https://service.canal-overseas.com/image-api/v1/image/a773200aaeb01b6932a66af052d8f843" />
</programme>
<programme start="20230507032158 +0200" stop="20230507040758 +0200" channel="CanalPlusActionCentre.af">
<title lang="fr">Fear The Walking Dead - S3 - Ep2</title>
<desc lang="fr">Aucune description</desc>
<category lang="fr">Inconnu</category>
<icon src="https://service.canal-overseas.com/image-api/v1/image/9b317bfc373922971b64492bffc0f8c7" />
</programme>
<programme start="20230507054010 +0200" stop="20230507061710 +0200" channel="CanalPlusActionCentre.af">
<title lang="fr">Halo - S1 - Ep5</title>
<desc lang="fr">Aucune description</desc>
<category lang="fr">Inconnu</category>
<icon src="https://service.canal-overseas.com/image-api/v1/image/f99312a778488a5c5c05292dfa7d6f94" />
</programme>
<programme start="20230507061802 +0200" stop="20230507070402 +0200" channel="CanalPlusActionCentre.af">
<title lang="fr">Halo - S1 - Ep6</title>
<desc lang="fr">Aucune description</desc>
<category lang="fr">Inconnu</category>
<icon src="https://service.canal-overseas.com/image-api/v1/image/24fdbff3661e0671bccdbdbfc7551677" />
</programme>