<!-- racacax\XmlTv\Component\Provider\Bouygues -->
<programme start="20230519050000 +0200" stop="20230519100000 +0200" channel="PinkTV.fr">
<title lang="fr">Rendez-vous à 0h</title>
<desc lang="fr">La chaîne Pink TV diffuse ses programmes à partir de minuit.</desc>
<category lang="fr">Programme</category>
<category lang="fr">Programme indéterminé</category>
<rating system="CSA"><value>-18</value><icon src="https://upload.wikimedia.org/wikipedia/commons/thumb/2/2d/Moins18.svg/200px-Moins18.svg.png" /></rating>
</programme>
<programme start="20230519100000 +0200" stop="20230519150000 +0200" channel="PinkTV.fr">
<title lang="fr">Rendez-vous à 0h</title>
<desc lang="fr">La chaîne Pink TV diffuse ses programmes à partir de minuit.</desc>
<category lang="fr">Programme</category>
<category lang="fr">Programme indéterminé</category>
<rating system="CSA"><value>-18</value><icon src="https://upload.wikimedia.org/wikipedia/commons/thumb/2/2d/Moins18.svg/200px-Moins18.svg.png" /></rating>
</programme>
<programme start="20230519150000 +0200" stop="20230519200000 +0200" channel="PinkTV.fr">
<title lang="fr">Rendez-vous à 0h</title>
<desc lang="fr">La chaîne Pink TV diffuse ses programmes à partir de minuit.</desc>
<category lang="fr">Programme</category>
<category lang="fr">Programme indéterminé</category>
<rating system="CSA"><value>-18</value><icon src="https://upload.wikimedia.org/wikipedia/commons/thumb/2/2d/Moins18.svg/200px-Moins18.svg.png" /></rating>
</programme>
<programme start="20230519200000 +0200" stop="20230520000000 +0200" channel="PinkTV.fr">
<title lang="fr">Rendez-vous à 0h</title>
<desc lang="fr">La chaîne Pink TV diffuse ses programmes à partir de minuit.</desc>
<category lang="fr">Programme</category>
<category lang="fr">Programme indéterminé</category>
<rating system="CSA"><value>-18</value><icon src="https://upload.wikimedia.org/wikipedia/commons/thumb/2/2d/Moins18.svg/200px-Moins18.svg.png" /></rating>
</programme>
<programme start="20230520000000 +0200" stop="20230520022000 +0200" channel="PinkTV.fr">
<title lang="fr">Surrender</title>
<desc lang="fr">Cocky Boys nous transporte dans un endroit assez fabuleux ou nos jeunes athlétes sont tous sexy, en slip blanc, en jeans avant de se déhabiller et rien nous cacher. Excellent film avec un trio en final !</desc>
<category lang="fr">Film</category>
<category lang="fr">Pornographie</category>
<rating system="CSA"><value>-18</value><icon src="https://upload.wikimedia.org/wikipedia/commons/thumb/2/2d/Moins18.svg/200px-Moins18.svg.png" /></rating>
</programme>
<programme start="20230520022000 +0200" stop="20230520032500 +0200" channel="PinkTV.fr">
<title lang="fr">L'étalon français</title>
<desc lang="fr">C'est au bois de Montmaur à Montpellier que Fabio Stallion fait la rencontre d'un autre sportif, Elias Roy. Un regard et un sourire les amènent à s'isoler pour baiser dans la garrigue. Elias profitera profond des 22 cm de l'étalon Fabio ! Le printemps est là dans le parc de la Feyssine à Villeurbanne, les bourgeons apparaissent sur le arbres, les oiseaux chantent et le jeune barbu Even Canaillou croise le regard d'un hétéro très curieux, Mathieu Delyon. Celui-ci cherche à se vider les couilles ! En chaleur, Canaillou saura prendre au fond de sa gorge puis de son cul les 22 cm du mâle en rut. Fabio &quot;22 cm&quot; Stallion est sur le point de partir du Koncept Sauna de Montpellier quand il croise le sexy Tommy &quot;23 cm&quot; Dreams. Persuasif, ce dernier le convainc de rester pour baiser dans les vestiaires.</desc>
<category lang="fr">Film</category>
<category lang="fr">Pornographie</category>
<rating system="CSA"><value>-18</value><icon src="https://upload.wikimedia.org/wikipedia/commons/thumb/2/2d/Moins18.svg/200px-Moins18.svg.png" /></rating>
</programme>
<programme start="20230520032500 +0200" stop="20230520044500 +0200" channel="PinkTV.fr">
<title lang="fr">New Arrivals</title>
<desc lang="fr">C'est peut-être l'un des premiers tournages porno en studio de Serg Shepard, mais il s'empresse de montrer à Xtian Wolf que ce n'est certainement pas la première fois qu'il se fait prendre par une grosse bite. Ce serait égoïste de la part des bodybuilders Nick Cranston et Davin Strong de garder leur divin physique divin rien que pour eux. Alors les beaux musclors s'empressent de se déshabiller pour montrer leur superbe musculature en action baise. Tony Genius et Jake Apton débutent ici leur première scène, Jake s'empalant avec délices sur le sexe dur de Tony. Le viril et rugueux Arturo Santos marteau-pilonne Greg Riley avec un plaisir qui donne envie de le connaître...</desc>
<category lang="fr">Film</category>
<category lang="fr">Pornographie</category>
<rating system="CSA"><value>-18</value><icon src="https://upload.wikimedia.org/wikipedia/commons/thumb/2/2d/Moins18.svg/200px-Moins18.svg.png" /></rating>
</programme>
<programme start="20230520044500 +0200" stop="20230520050000 +0200" channel="PinkTV.fr">
<title lang="fr">Best of Cadinot : L'insatiable, scène 3</title>
<desc lang="fr">L'Insatiable ne trompe personne, il aime tout le monde, mais refuse d'être soumis et enfermé par son ami possessif : rues, squares, discothèques ou backrooms, deux, trois, quatre ou cinq, il comble les fantasmes des beaux gosses qui croisent sa route. Quinze minets hyper montés sont les héros de leur propre vie : violence, passion, émotion, tendresse, réalisme éclaboussant de vérité...</desc>
<category lang="fr">Film</category>
<category lang="fr">Pornographie</category>
<rating system="CSA"><value>-18</value><icon src="https://upload.wikimedia.org/wikipedia/commons/thumb/2/2d/Moins18.svg/200px-Moins18.svg.png" /></rating>
</programme>
<programme start="20230520050000 +0200" stop="20230520100000 +0200" channel="PinkTV.fr">
<title lang="fr">Rendez-vous à 0h</title>
<desc lang="fr">La chaîne Pink TV diffuse ses programmes à partir de minuit.</desc>
<category lang="fr">Programme</category>
<category lang="fr">Programme indéterminé</category>
<rating system="CSA"><value>-18</value><icon src="https://upload.wikimedia.org/wikipedia/commons/thumb/2/2d/Moins18.svg/200px-Moins18.svg.png" /></rating>
</programme>