<!-- racacax\XmlTv\Component\Provider\Orange -->
<programme start="20230516224300 +0200" stop="20230517001100 +0200" channel="PLANETEJustice.fr">
<title lang="fr">Faites entrer l'accusé</title>
<desc lang="fr">Quand Nadine Chabert disparaît à Istres, le 10 juin 2003, les soupçons convergent rapidement vers Patrick, son mari. Il hésite, se contredit dans ses déclarations et finit par être emprisonné, bien qu'il clame son innocence. Avec sa fille, sa belle-mère et ses avocats, Patrick Chabert entame un...</desc>
<category lang="fr">Magazine</category>
<category lang="fr">Mag. Société</category>
<icon src="https://proxymedia.woopic.com/api/v1/images/340%2F/43_EMI_12165372.jpg" />
<rating system="CSA"><value>-12</value><icon src="https://upload.wikimedia.org/wikipedia/commons/thumb/b/b5/Moins12.svg/200px-Moins12.svg.png" /></rating>
</programme>
<programme start="20230517001100 +0200" stop="20230517005200 +0200" channel="PLANETEJustice.fr">
<title lang="fr">48 heures pour un crime</title>
<desc lang="fr">Les policiers de Tulsa enquêtent sur les Neighborhood Crips pour résoudre le meurtre d'un jeune homme qui a tenté de quitter le gang.</desc>
<category lang="fr">Documentaire</category>
<category lang="fr">Doc. Société</category>
<icon src="https://proxymedia.woopic.com/api/v1/images/340%2F/43_EMI_29986941.jpg" />
<rating system="CSA"><value>-10</value><icon src="https://upload.wikimedia.org/wikipedia/commons/thumb/b/bf/Moins10.svg/200px-Moins10.svg.png" /></rating>
</programme>
<programme start="20230517005200 +0200" stop="20230517013800 +0200" channel="PLANETEJustice.fr">
<title lang="fr">48 heures pour un crime</title>
<desc lang="fr">A Atlanta, un homme est assassiné après avoir surpris un voleur à son domicile, tandis qu'à Tulsa, la confrontation entre deux membres de gangs finit mal.</desc>
<category lang="fr">Documentaire</category>
<category lang="fr">Doc. Société</category>
<icon src="https://proxymedia.woopic.com/api/v1/images/340%2F/43_EMI_17406042.jpg" />
<rating system="CSA"><value>-10</value><icon src="https://upload.wikimedia.org/wikipedia/commons/thumb/b/bf/Moins10.svg/200px-Moins10.svg.png" /></rating>
</programme>
<programme start="20230517013800 +0200" stop="20230517024300 +0200" channel="PLANETEJustice.fr">
<title lang="fr">Alerte kidnapping</title>
<desc lang="fr">Retour sur l'enlèvement de l'ancien bourgmestre de Saint-Josse, Guy Cudell, en 1984, à travers des images d'archives et des témoignages</desc>
<category lang="fr">Documentaire</category>
<category lang="fr">Doc. Société</category>
<icon src="https://proxymedia.woopic.com/api/v1/images/340%2F/43_EMI_37526006.jpg" />
<rating system="CSA"><value>-10</value><icon src="https://upload.wikimedia.org/wikipedia/commons/thumb/b/bf/Moins10.svg/200px-Moins10.svg.png" /></rating>
</programme>
<programme start="20230517024300 +0200" stop="20230517040800 +0200" channel="PLANETEJustice.fr">
<title lang="fr">The Wimbledon Kidnapping</title>
<desc lang="fr">En 1969, Muriel McKay, l'épouse de l'un des plus proches collaborateurs du magnat de la presse Rupert Murdoch, est enlevée à son domicile de Wimbledon.</desc>
<category lang="fr">Documentaire</category>
<category lang="fr">Doc. Société</category>
<icon src="https://proxymedia.woopic.com/api/v1/images/340%2F/43_EMI_35236960.jpg" />
<rating system="CSA"><value>-10</value><icon src="https://upload.wikimedia.org/wikipedia/commons/thumb/b/bf/Moins10.svg/200px-Moins10.svg.png" /></rating>
</programme>
<programme start="20230517040800 +0200" stop="20230517050700 +0200" channel="PLANETEJustice.fr">
<title lang="fr">Interruption des programmes</title>
<desc lang="fr">Autre.</desc>
<category lang="fr">Autre</category>
<icon src="https://proxymedia.woopic.com/api/v1/images/340%2F/43_GEP_11082754.jpg" />
<rating system="CSA"><value>Tout public</value></rating>
</programme>
<programme start="20230517050700 +0200" stop="20230517052700 +0200" channel="PLANETEJustice.fr">
<title lang="fr">J'ai échappé à un serial killer</title>
<desc lang="fr">Des années après avoir été agressée, Holly Dunn, alors étudiante à l'université du Kentucky, append qu'elle est la seule rescapée des victimes d'Angel Maturino Reséndiz.</desc>
<category lang="fr">Documentaire</category>
<category lang="fr">Doc. Société</category>
<icon src="https://proxymedia.woopic.com/api/v1/images/340%2F/43_COL_27666491.jpg" />
<rating system="CSA"><value>-10</value><icon src="https://upload.wikimedia.org/wikipedia/commons/thumb/b/bf/Moins10.svg/200px-Moins10.svg.png" /></rating>
</programme>
<programme start="20230517052700 +0200" stop="20230517054900 +0200" channel="PLANETEJustice.fr">
<title lang="fr">J'ai échappé à un serial killer</title>
<desc lang="fr">En novembre 1984, Lisa McVey Noland, 17 ans, employée dans un magasin de beignets de Tampa, rentre de nuit à vélo lorsqu'elle est enlevée par Bobby Joe Long.</desc>
<category lang="fr">Documentaire</category>
<category lang="fr">Doc. Société</category>
<icon src="https://proxymedia.woopic.com/api/v1/images/340%2F/43_COL_27666491.jpg" />
<rating system="CSA"><value>-10</value><icon src="https://upload.wikimedia.org/wikipedia/commons/thumb/b/bf/Moins10.svg/200px-Moins10.svg.png" /></rating>
</programme>
<programme start="20230517054900 +0200" stop="20230517063400 +0200" channel="PLANETEJustice.fr">
<title lang="fr">Liverpool Narcos</title>
<desc lang="fr">Dans les années 1990, l'augmentation de l'offre et la baisse des prix a fait exploser la consommation de cocaïne, jusque-là réservée aux plus aisés.</desc>
<category lang="fr">Documentaire</category>
<category lang="fr">Doc. Société</category>
<icon src="https://proxymedia.woopic.com/api/v1/images/340%2F/43_EMI_33016274.jpg" />
<rating system="CSA"><value>-10</value><icon src="https://upload.wikimedia.org/wikipedia/commons/thumb/b/bf/Moins10.svg/200px-Moins10.svg.png" /></rating>
</programme>
<programme start="20230517063400 +0200" stop="20230517072700 +0200" channel="PLANETEJustice.fr">
<title lang="fr">Enquêtes criminelles</title>
<desc lang="fr">En 2006, Raphael Lomoro, parti à Madagascar pour se lancer dans la culture de la vanille, rentre en France pou passer Noël en famille, avant de disparaître.</desc>
<category lang="fr">Magazine</category>
<category lang="fr">Mag. Société</category>
<icon src="https://proxymedia.woopic.com/api/v1/images/340%2F/43_COL_10356816.jpg" />
<rating system="CSA"><value>-10</value><icon src="https://upload.wikimedia.org/wikipedia/commons/thumb/b/bf/Moins10.svg/200px-Moins10.svg.png" /></rating>
</programme>
<programme start="20230517073800 +0200" stop="20230517084000 +0200" channel="PLANETEJustice.fr">
<title lang="fr">Nisman : le procureur, la présidente et l'espion</title>
<desc lang="fr">Espion argentin redouté, Jaime Stiuso s'exprime pour la première fois devant une caméra pour raconter comment il a aidé Nisman dans ses enquêtes.</desc>
<category lang="fr">Documentaire</category>
<category lang="fr">Doc. Société</category>
<icon src="https://proxymedia.woopic.com/api/v1/images/340%2F/43_EMI_21976163.jpg" />
<rating system="CSA"><value>-10</value><icon src="https://upload.wikimedia.org/wikipedia/commons/thumb/b/bf/Moins10.svg/200px-Moins10.svg.png" /></rating>
</programme>
<programme start="20230517084000 +0200" stop="20230517092200 +0200" channel="PLANETEJustice.fr">
<title lang="fr">Mineurs en prison</title>
<desc lang="fr">Condamné à l'âge de 17 ans, Richard Kinder, qui a purgé près de 50 ans d'une peine à perpétuité sans possibilité de libération conditionnelle, espère être libéré.</desc>
<category lang="fr">Documentaire</category>
<category lang="fr">Doc. Société</category>
<icon src="https://proxymedia.woopic.com/api/v1/images/340%2F/43_EMI_29988181.jpg" />
<rating system="CSA"><value>-10</value><icon src="https://upload.wikimedia.org/wikipedia/commons/thumb/b/bf/Moins10.svg/200px-Moins10.svg.png" /></rating>
</programme>
<programme start="20230517092200 +0200" stop="20230517100700 +0200" channel="PLANETEJustice.fr">
<title lang="fr">Mineurs en prison</title>
<desc lang="fr">Malcolm Thrower, condamné à l'âge de 17 ans pour meurtre, espère pouvoir bénéficier d'une réduction de peine et obtenir le pardon de la famille de sa victime.</desc>
<category lang="fr">Documentaire</category>
<category lang="fr">Doc. Société</category>
<icon src="https://proxymedia.woopic.com/api/v1/images/340%2F/43_EMI_29916056.jpg" />
<rating system="CSA"><value>-10</value><icon src="https://upload.wikimedia.org/wikipedia/commons/thumb/b/bf/Moins10.svg/200px-Moins10.svg.png" /></rating>
</programme>
<programme start="20230517100700 +0200" stop="20230517105300 +0200" channel="PLANETEJustice.fr">
<title lang="fr">Meurtres sous surveillance</title>
<desc lang="fr">Le service de police de Calgary espère localiser Ryan Lane, qui a mystérieusement disparu après un appel téléphonique, grâce aux images de vidéosurveillance.</desc>
<category lang="fr">Documentaire</category>
<category lang="fr">Doc. Société</category>
<icon src="https://proxymedia.woopic.com/api/v1/images/340%2F/43_EMI_27919363.jpg" />
<rating system="CSA"><value>-10</value><icon src="https://upload.wikimedia.org/wikipedia/commons/thumb/b/bf/Moins10.svg/200px-Moins10.svg.png" /></rating>
</programme>
<programme start="20230517105300 +0200" stop="20230517114700 +0200" channel="PLANETEJustice.fr">
<title lang="fr">Meurtres sous surveillance</title>
<desc lang="fr">La police visionne les images de vidéosurveillance pour trouver des informations sur les dernières heures d'Amanda Douglas et Jennifer Sudar Sanders, abattues en plein jour.</desc>
<category lang="fr">Documentaire</category>
<category lang="fr">Doc. Société</category>
<icon src="https://proxymedia.woopic.com/api/v1/images/340%2F/43_EMI_28259613.jpg" />
<rating system="CSA"><value>-10</value><icon src="https://upload.wikimedia.org/wikipedia/commons/thumb/b/bf/Moins10.svg/200px-Moins10.svg.png" /></rating>
</programme>
<programme start="20230517114700 +0200" stop="20230517132000 +0200" channel="PLANETEJustice.fr">
<title lang="fr">Faites entrer l'accusé</title>
<desc lang="fr">Sébastien Brun, un fleuriste de Grenoble, commerçant prospère et ambitieux, jeune papa heureux en ménage depuis quatre ans avec Denize Soares, une jeune Brésilienne, décide de tout quitter sur un coup de tête pour refaire sa vie au Brésil. Les talents de manipulatrice de Denize n'en sont qu'à...</desc>
<category lang="fr">Magazine</category>
<category lang="fr">Mag. Société</category>
<icon src="https://proxymedia.woopic.com/api/v1/images/340%2F/43_EMI_17077315.jpg" />
<rating system="CSA"><value>-10</value><icon src="https://upload.wikimedia.org/wikipedia/commons/thumb/b/bf/Moins10.svg/200px-Moins10.svg.png" /></rating>
</programme>
<programme start="20230517132000 +0200" stop="20230517141300 +0200" channel="PLANETEJustice.fr">
<title lang="fr">Enquêtes criminelles</title>
<desc lang="fr">Samira, 20 ans, entretient depuis quelques temps une liaison passionnelle avec Maël. Le 1er mars 2011, les deux tourtereaux disparaissent mystérieusement. Alors qu'une escapade en amoureux reste une possibilité, un automobiliste italien fait une terrible découverte.</desc>
<category lang="fr">Magazine</category>
<category lang="fr">Mag. Société</category>
<icon src="https://proxymedia.woopic.com/api/v1/images/340%2F/43_EMI_33326698.jpg" />
<rating system="CSA"><value>-10</value><icon src="https://upload.wikimedia.org/wikipedia/commons/thumb/b/bf/Moins10.svg/200px-Moins10.svg.png" /></rating>
</programme>
<programme start="20230517141300 +0200" stop="20230517154700 +0200" channel="PLANETEJustice.fr">
<title lang="fr">Marseille Story, une histoire de la violence</title>
<desc lang="fr">Une histoire de la violence à Marseille, une ville au fort taux de criminalité : Louis XIV déjà se méfiait du caractère insurrectionnel de ses habitants.</desc>
<category lang="fr">Documentaire</category>
<category lang="fr">Doc. Société</category>
<icon src="https://proxymedia.woopic.com/api/v1/images/340%2F/43_EMI_10354052.jpg" />
<rating system="CSA"><value>-10</value><icon src="https://upload.wikimedia.org/wikipedia/commons/thumb/b/bf/Moins10.svg/200px-Moins10.svg.png" /></rating>
</programme>
<programme start="20230517154700 +0200" stop="20230517170600 +0200" channel="PLANETEJustice.fr">
<title lang="fr">Faites entrer l'accusé</title>
<desc lang="fr">A sa retraite, André Le Floc'h achète &quot;L'Intermezzo&quot;, un superbe bateau à voile qu'il avait remarqué lors de la course du Rhum, et part faire le tour du monde. Au Portugal, durant l'été 2006, il trouve la mort en croisant la route de Thierry Beille et Corinne Caspar, qui l'assassinent pour lui...</desc>
<category lang="fr">Magazine</category>
<category lang="fr">Mag. Société</category>
<icon src="https://proxymedia.woopic.com/api/v1/images/340%2F/43_EMI_26513501.jpg" />
<rating system="CSA"><value>-10</value><icon src="https://upload.wikimedia.org/wikipedia/commons/thumb/b/bf/Moins10.svg/200px-Moins10.svg.png" /></rating>
</programme>
<programme start="20230517170600 +0200" stop="20230517174700 +0200" channel="PLANETEJustice.fr">
<title lang="fr">48 heures pour un crime</title>
<desc lang="fr">A Tulsa, dans un parking, un sans-abri est tué par une voiture : les policiers mettent tout en oeuvre pour retrouver le conducteur en cause.</desc>
<category lang="fr">Documentaire</category>
<category lang="fr">Doc. Société</category>
<icon src="https://proxymedia.woopic.com/api/v1/images/340%2F/43_COL_26735001.jpg" />
<rating system="CSA"><value>-10</value><icon src="https://upload.wikimedia.org/wikipedia/commons/thumb/b/bf/Moins10.svg/200px-Moins10.svg.png" /></rating>
</programme>
<programme start="20230517174700 +0200" stop="20230517183200 +0200" channel="PLANETEJustice.fr">
<title lang="fr">48 heures pour un crime</title>
<desc lang="fr">A Tulsa, un homme a appelé le 911 en affirmant que sa petite amie s'était suicidée par balle : sur place, les policiers pensent qu'elle a plutôt été victime d'un acte criminel.</desc>
<category lang="fr">Documentaire</category>
<category lang="fr">Doc. Société</category>
<icon src="https://proxymedia.woopic.com/api/v1/images/340%2F/43_EMI_13430908.jpg" />
<rating system="CSA"><value>-10</value><icon src="https://upload.wikimedia.org/wikipedia/commons/thumb/b/bf/Moins10.svg/200px-Moins10.svg.png" /></rating>
</programme>
<programme start="20230517183200 +0200" stop="20230517191700 +0200" channel="PLANETEJustice.fr">
<title lang="fr">Les maîtres du crime</title>
<desc lang="fr">Quand Wayne Capelli est assassiné, les policiers découvrent que cet homme modeste avait souscrit une importante assurance vie, ils sont très surpris.</desc>
<category lang="fr">Documentaire</category>
<category lang="fr">Doc. Société</category>
<icon src="https://proxymedia.woopic.com/api/v1/images/340%2F/43_EMI_23171434.jpg" />
<rating system="CSA"><value>-10</value><icon src="https://upload.wikimedia.org/wikipedia/commons/thumb/b/bf/Moins10.svg/200px-Moins10.svg.png" /></rating>
</programme>
<programme start="20230517191700 +0200" stop="20230517200200 +0200" channel="PLANETEJustice.fr">
<title lang="fr">Les maîtres du crime</title>
<desc lang="fr">Après un appel signalant une fusillade, la police se rend sur le parking d'un centre commercial et découvre une femme, abattue au volant de son véhicule.</desc>
<category lang="fr">Documentaire</category>
<category lang="fr">Doc. Société</category>
<icon src="https://proxymedia.woopic.com/api/v1/images/340%2F/43_EMI_26301502.jpg" />
<rating system="CSA"><value>-10</value><icon src="https://upload.wikimedia.org/wikipedia/commons/thumb/b/bf/Moins10.svg/200px-Moins10.svg.png" /></rating>
</programme>
<programme start="20230517200200 +0200" stop="20230517210000 +0200" channel="PLANETEJustice.fr">
<title lang="fr">Alerte enlèvement</title>
<desc lang="fr">Le 15 août 2015, à Rennes, Rifki, 4 ans, est enlevé par une connaissance de son oncle, le lendemain matin, le plan &quot;Alerte Enlèvement&quot; est déclenché.</desc>
<category lang="fr">Documentaire</category>
<category lang="fr">Doc. Société</category>
<icon src="https://proxymedia.woopic.com/api/v1/images/340%2F/43_EMI_10354031.jpg" />
<rating system="CSA"><value>-10</value><icon src="https://upload.wikimedia.org/wikipedia/commons/thumb/b/bf/Moins10.svg/200px-Moins10.svg.png" /></rating>
</programme>
<programme start="20230517210000 +0200" stop="20230517214000 +0200" channel="PLANETEJustice.fr">
<title lang="fr">Petits meurtres en Californie *2020</title>
<desc lang="fr">En avril 2003, à Placentia, un jeune couple est abattu dans sa voiture en pleine rue et en plein jour, plongeant la ville dans la peur. Le tueur est en fuite.</desc>
<category lang="fr">Documentaire</category>
<category lang="fr">Doc. Société</category>
<icon src="https://proxymedia.woopic.com/api/v1/images/340%2F/43_EMI_30364440.jpg" />
<rating system="CSA"><value>-10</value><icon src="https://upload.wikimedia.org/wikipedia/commons/thumb/b/bf/Moins10.svg/200px-Moins10.svg.png" /></rating>
</programme>
<programme start="20230517214000 +0200" stop="20230517222800 +0200" channel="PLANETEJustice.fr">
<title lang="fr">Petits meurtres en Californie *2020</title>
<desc lang="fr">Mario Rodriguez, un joailler de 68 ans, a disparu alors qu'il transportait une importante quantité de bijoux. Son véhicule est retrouvé quelques jours plus tard.</desc>
<category lang="fr">Documentaire</category>
<category lang="fr">Doc. Société</category>
<icon src="https://proxymedia.woopic.com/api/v1/images/340%2F/43_COL_37452654.jpg" />
<rating system="CSA"><value>-10</value><icon src="https://upload.wikimedia.org/wikipedia/commons/thumb/b/bf/Moins10.svg/200px-Moins10.svg.png" /></rating>
</programme>
<programme start="20230517222800 +0200" stop="20230517230800 +0200" channel="PLANETEJustice.fr">
<title lang="fr">Petits meurtres en Californie *2020</title>
<desc lang="fr">Sur les lieux d'un braquage, un homme grièvement blessé s'effondre devant les policiers, et une femme morte est découverte à l'intérieur de la boutique.</desc>
<category lang="fr">Documentaire</category>
<category lang="fr">Doc. Société</category>
<icon src="https://proxymedia.woopic.com/api/v1/images/340%2F/43_COL_37452654.jpg" />
<rating system="CSA"><value>-10</value><icon src="https://upload.wikimedia.org/wikipedia/commons/thumb/b/bf/Moins10.svg/200px-Moins10.svg.png" /></rating>
</programme>
<programme start="20230517230800 +0200" stop="20230517235200 +0200" channel="PLANETEJustice.fr">
<title lang="fr">Petits meurtres en Californie *2020</title>
<desc lang="fr">En novembre 2003, dans un coin isolé de la ville d'Orange, le corps d'un adolescent de 17 ans est découvert, tué par balles et incendié.</desc>
<category lang="fr">Documentaire</category>
<category lang="fr">Doc. Société</category>
<icon src="https://proxymedia.woopic.com/api/v1/images/340%2F/43_COL_37452654.jpg" />
<rating system="CSA"><value>-10</value><icon src="https://upload.wikimedia.org/wikipedia/commons/thumb/b/bf/Moins10.svg/200px-Moins10.svg.png" /></rating>
</programme>
<programme start="20230517235200 +0200" stop="20230518004700 +0200" channel="PLANETEJustice.fr">
<title lang="fr">Vandales du rail : les graffeurs face à la justice</title>
<desc lang="fr">En 2001, une enquête a conduit une soixantaine de taggeurs devant le tribunal de Versailles pour des dégradations commises dans les transports en commun.</desc>
<category lang="fr">Documentaire</category>
<category lang="fr">Doc. Société</category>
<icon src="https://proxymedia.woopic.com/api/v1/images/340%2F/43_EMI_37989356.jpg" />
<rating system="CSA"><value>Tout public</value></rating>
</programme>